app02/__init__.py
app02/__main__.py
app02/internal/__build_channel__.py
app02/internal/__init__.py
app02/matt/__init__.py
app02/matt/math_add.py
app02/matt/show_num.py
app02-0.1.0.dist-info/AUTHORS.rst
app02-0.1.0.dist-info/LICENSE
app02-0.1.0.dist-info/METADATA
app02-0.1.0.dist-info/WHEEL
app02-0.1.0.dist-info/entry_points.txt
app02-0.1.0.dist-info/top_level.txt
app02-0.1.0.dist-info/RECORD
