Metadata-Version: 2.1
Name: app02
Version: 0.1.0
Summary: this is my app
Home-page: https://github.com/near2sea/app02
Author: lihaijian
Author-email: sanan.li@qq.com
License: BSD license
Keywords: app02
Classifier: Development Status :: 2 - Pre-Alpha
Classifier: Intended Audience :: Developers
Classifier: License :: OSI Approved :: BSD License
Classifier: Programming Language :: Python
Classifier: Programming Language :: Python :: 3 :: Only
Classifier: Topic :: Utilities
Requires-Python: >=3.6
License-File: LICENSE
License-File: AUTHORS.rst
Requires-Dist: pip
Requires-Dist: setuptools
Provides-Extra: dev
Requires-Dist: pytest ; extra == 'dev'
Requires-Dist: pytest-mock ; extra == 'dev'
Requires-Dist: flake8 ; extra == 'dev'
Requires-Dist: flake8-comprehensions ; extra == 'dev'
Requires-Dist: flake8-deprecated ; extra == 'dev'
Requires-Dist: flake8-mutable ; extra == 'dev'
Requires-Dist: flake8-tuple ; extra == 'dev'
Requires-Dist: pytest-cov ; extra == 'dev'
Requires-Dist: pyyaml ; extra == 'dev'
Requires-Dist: twine ; extra == 'dev'
Requires-Dist: wheel ; extra == 'dev'
Provides-Extra: test
Requires-Dist: pytest ; extra == 'test'
Requires-Dist: pytest-mock ; extra == 'test'
